{
  "9NK13T4QFPQW": {
    "productTitle": "EA SPORTS FC™ 26 Xbox One",
    "productId": "9NK13T4QFPQW",
    "developerName": "EA CANADA",
    "publisherName": "Electronic Arts",
    "categories": [
      "Sports",
      "Simulation"
    ],
    "productDescription": "The Club is Yours in EA SPORTS FC™ 26.\n\nExperience The World’s Game like never before in EA SPORTS FC™ 26. The latest update introduces a brand-new international tournament mode featuring 48 national teams, alongside new authentic stadiums to play in. Take on international-themed Manager Live Challenges, and step into Player Career with new international ICONs and Heroes.\nPlay your way with an overhauled gameplay experience shaped by community feedback, Manager Live Challenges that deliver fresh scenarios throughout the season, and new Archetypes inspired by greats of the game.\n\nPut your dream squad to the test in Football Ultimate Team™ with new Live Events and Tournament modes, as well as a refreshed Rivals and Champs experience.\nExperience The World’s Game like never before in EA SPORTS FC™ 26, with match data from the world’s top leagues powering 20,000+ authentic players.\n\nThis game includes optional in-game purchases of virtual currency that can be used to acquire virtual in-game items, including a random selection of virtual in-game items.\n\nConditions & restrictions apply. See ea.com/legal/legal-disclosures for details.\n\nConditions & restrictions apply. See ea.com/games/ea-sports-fc/fc-26/game-disclaimers for details.\n\nFC Points purchase is not available in Belgium and South Korea.\n\nAudio commentary for languages other than English and the console-settings language requires a separate download.\n\n© 2025 Electronic Arts Inc. Electronic Arts, EA, EA SPORTS, the EA SPORTS logo, EA SPORTS FC, the EA SPORTS FC logo, Frostbite, the Frostbite logo, Football Ultimate Team, and Ultimate Team are trademarks of Electronic Arts Inc.",
    "images": {
      "Screenshot": [
        "https://store-images.s-microsoft.com/image/apps.36288.13628388140711442.b4288d99-175c-4445-b6fe-03ffee0457a3.06840614-bdc1-4548-9483-b5f4d85b13c1",
        "https://store-images.s-microsoft.com/image/apps.63630.13665948255535452.d93b5d6d-aaa5-4c34-95b4-e4a25c2d92e5.205c1f38-4c98-4523-8117-e50355738a32",
        "https://store-images.s-microsoft.com/image/apps.37750.13628388140711442.b4288d99-175c-4445-b6fe-03ffee0457a3.3c4325c8-275a-4676-b17b-0c2544071934",
        "https://store-images.s-microsoft.com/image/apps.28420.13628388140711442.b4288d99-175c-4445-b6fe-03ffee0457a3.dbe7855d-d339-447f-b89e-845dacfb69b3",
        "https://store-images.s-microsoft.com/image/apps.32259.13628388140711442.b4288d99-175c-4445-b6fe-03ffee0457a3.d06c3994-ecc6-4cbb-b10e-45601efc3710",
        "https://store-images.s-microsoft.com/image/apps.10703.13628388140711442.b4288d99-175c-4445-b6fe-03ffee0457a3.d4bdcc84-5c50-4661-bff8-80c7f10bf076",
        "https://store-images.s-microsoft.com/image/apps.39247.13628388140711442.b4288d99-175c-4445-b6fe-03ffee0457a3.ed8fb24b-5f05-4486-bc9b-e228c0fdabfe",
        "https://store-images.s-microsoft.com/image/apps.65064.13628388140711442.b4288d99-175c-4445-b6fe-03ffee0457a3.7a6126c1-7ce8-4fde-945e-cb3b67800096",
        "https://store-images.s-microsoft.com/image/apps.45134.13628388140711442.b4288d99-175c-4445-b6fe-03ffee0457a3.e467882e-01da-4164-8868-0b967d780014",
        "https://store-images.s-microsoft.com/image/apps.27033.13628388140711442.b4288d99-175c-4445-b6fe-03ffee0457a3.7fbc0cfc-4387-4721-b8da-3ddb52b24315",
        "https://store-images.s-microsoft.com/image/apps.45103.13628388140711442.b4288d99-175c-4445-b6fe-03ffee0457a3.19dc0dca-faba-424e-bc3b-5d17e55136cd",
        "https://store-images.s-microsoft.com/image/apps.17491.13628388140711442.b4288d99-175c-4445-b6fe-03ffee0457a3.bf94a19c-7ae1-458f-87c8-0714f9eebb11",
        "https://store-images.s-microsoft.com/image/apps.1588.13628388140711442.b4288d99-175c-4445-b6fe-03ffee0457a3.795a0d24-f477-4d80-bf57-a388f2755a36"
      ],
      "Poster": [
        "https://store-images.s-microsoft.com/image/apps.7574.13665948255535452.6d8553bd-d6c9-4090-869c-05032efb323d.6ca71ea2-7a36-444d-9de1-ad47842ec246"
      ],
      "TitledHeroArt": [
        "https://store-images.s-microsoft.com/image/apps.23154.13665948255535452.6d8553bd-d6c9-4090-869c-05032efb323d.33837f28-7855-46be-891e-94a8f33850d2"
      ],
      "SuperHeroArt": [
        "https://store-images.s-microsoft.com/image/apps.45937.13665948255535452.6d8553bd-d6c9-4090-869c-05032efb323d.e8288a32-e4b7-4886-ba27-cba2b6a09a13"
      ],
      "BoxArt": [
        "https://store-images.s-microsoft.com/image/apps.37689.13665948255535452.6d8553bd-d6c9-4090-869c-05032efb323d.46a85de8-1e53-4579-a8d7-62fc04d422ac"
      ],
      "FeaturePromotionalSquareArt": [
        "https://store-images.s-microsoft.com/image/apps.26461.13665948255535452.6d8553bd-d6c9-4090-869c-05032efb323d.f7ff2a6d-61b5-4ae5-a251-591f2aa77a2b"
      ]
    },
    "releaseDate": "9998-12-30T00:00:00.0000000Z",
    "userRating": 3,
    "pricing": {
      "currencyCode": "EUR",
      "ListPrice": 0,
      "MSRP": 0,
      "WholesalePrice": null
    }
  },
  "9P9FTXPKQ35P": {
    "productTitle": "EA SPORTS FC™ 26 Xbox Series X|S",
    "productId": "9P9FTXPKQ35P",
    "developerName": "EA CANADA",
    "publisherName": "Electronic Arts",
    "categories": [
      "Sports",
      "Simulation"
    ],
    "productDescription": "The Club is Yours in EA SPORTS FC™ 26.\n\nExperience The World’s Game like never before in EA SPORTS FC™ 26. The latest update introduces a brand-new international tournament mode featuring 48 national teams, alongside new authentic stadiums to play in. Take on international-themed Manager Live Challenges, and step into Player Career with new international ICONs and Heroes.\nPlay your way with an overhauled gameplay experience shaped by community feedback, Manager Live Challenges that deliver fresh scenarios throughout the season, and new Archetypes inspired by greats of the game.\n\nPut your dream squad to the test in Football Ultimate Team™ with new Live Events and Tournament modes, as well as a refreshed Rivals and Champs experience.\nExperience The World’s Game like never before in EA SPORTS FC™ 26, with match data from the world’s top leagues powering 20,000+ authentic players.\n\nThis game includes optional in-game purchases of virtual currency that can be used to acquire virtual in-game items, including a random selection of virtual in-game items.\n\nConditions & restrictions apply. See ea.com/legal/legal-disclosures for details.\n\nConditions & restrictions apply. See ea.com/games/ea-sports-fc/fc-26/game-disclaimers for details.\n\nFC Points purchase is not available in Belgium and South Korea.\n\nAudio commentary for languages other than English and the console-settings language requires a separate download.\n\n© 2025 Electronic Arts Inc. Electronic Arts, EA, EA SPORTS, the EA SPORTS logo, EA SPORTS FC, the EA SPORTS FC logo, Frostbite, the Frostbite logo, Football Ultimate Team, and Ultimate Team are trademarks of Electronic Arts Inc.",
    "images": {
      "Screenshot": [
        "https://store-images.s-microsoft.com/image/apps.36288.13628388140711442.b4288d99-175c-4445-b6fe-03ffee0457a3.06840614-bdc1-4548-9483-b5f4d85b13c1",
        "https://store-images.s-microsoft.com/image/apps.63630.14143997528953872.c53b74e0-5dc5-48e0-8017-b7e14664f22f.19385d5e-d2a7-4cde-8632-4fa41c9cd8ef",
        "https://store-images.s-microsoft.com/image/apps.37750.13628388140711442.b4288d99-175c-4445-b6fe-03ffee0457a3.3c4325c8-275a-4676-b17b-0c2544071934",
        "https://store-images.s-microsoft.com/image/apps.28420.13628388140711442.b4288d99-175c-4445-b6fe-03ffee0457a3.dbe7855d-d339-447f-b89e-845dacfb69b3",
        "https://store-images.s-microsoft.com/image/apps.32259.13628388140711442.b4288d99-175c-4445-b6fe-03ffee0457a3.d06c3994-ecc6-4cbb-b10e-45601efc3710",
        "https://store-images.s-microsoft.com/image/apps.10703.13628388140711442.b4288d99-175c-4445-b6fe-03ffee0457a3.d4bdcc84-5c50-4661-bff8-80c7f10bf076",
        "https://store-images.s-microsoft.com/image/apps.39247.13628388140711442.b4288d99-175c-4445-b6fe-03ffee0457a3.ed8fb24b-5f05-4486-bc9b-e228c0fdabfe",
        "https://store-images.s-microsoft.com/image/apps.65064.13628388140711442.b4288d99-175c-4445-b6fe-03ffee0457a3.7a6126c1-7ce8-4fde-945e-cb3b67800096",
        "https://store-images.s-microsoft.com/image/apps.45134.13628388140711442.b4288d99-175c-4445-b6fe-03ffee0457a3.e467882e-01da-4164-8868-0b967d780014",
        "https://store-images.s-microsoft.com/image/apps.27033.13628388140711442.b4288d99-175c-4445-b6fe-03ffee0457a3.7fbc0cfc-4387-4721-b8da-3ddb52b24315",
        "https://store-images.s-microsoft.com/image/apps.45103.13628388140711442.b4288d99-175c-4445-b6fe-03ffee0457a3.19dc0dca-faba-424e-bc3b-5d17e55136cd",
        "https://store-images.s-microsoft.com/image/apps.17491.13628388140711442.b4288d99-175c-4445-b6fe-03ffee0457a3.bf94a19c-7ae1-458f-87c8-0714f9eebb11",
        "https://store-images.s-microsoft.com/image/apps.1588.13628388140711442.b4288d99-175c-4445-b6fe-03ffee0457a3.795a0d24-f477-4d80-bf57-a388f2755a36"
      ],
      "Poster": [
        "https://store-images.s-microsoft.com/image/apps.7574.14143997528953872.47f85861-9d63-490a-8d39-2fda8228a3ec.eec7cad1-ab84-4cb6-a8e7-6c2acf5ba10f"
      ],
      "BoxArt": [
        "https://store-images.s-microsoft.com/image/apps.37689.14143997528953872.47f85861-9d63-490a-8d39-2fda8228a3ec.808e0994-b5f5-401d-9393-a8a356945694"
      ],
      "SuperHeroArt": [
        "https://store-images.s-microsoft.com/image/apps.45937.14143997528953872.47f85861-9d63-490a-8d39-2fda8228a3ec.4671e05d-4068-4ef5-b867-cf5827056f3a"
      ],
      "TitledHeroArt": [
        "https://store-images.s-microsoft.com/image/apps.23154.14143997528953872.47f85861-9d63-490a-8d39-2fda8228a3ec.3c18fd31-9441-4933-aed0-69ebf59b30d3"
      ],
      "FeaturePromotionalSquareArt": [
        "https://store-images.s-microsoft.com/image/apps.26461.14143997528953872.47f85861-9d63-490a-8d39-2fda8228a3ec.43fed37a-c44a-4173-bcff-cc7d148631eb"
      ]
    },
    "releaseDate": "9998-12-30T00:00:00.0000000Z",
    "userRating": 2.5,
    "pricing": {
      "currencyCode": "EUR",
      "ListPrice": 0,
      "MSRP": 0,
      "WholesalePrice": null
    }
  },
  "9PC1KTWW5PB5": {
    "productTitle": "NHL® 26 Xbox Series X|S",
    "productId": "9PC1KTWW5PB5",
    "developerName": "EA Vancouver",
    "publisherName": "Electronic Arts",
    "categories": [
      "Sports"
    ],
    "productDescription": "Step onto the ice and into the record books with generational talent, beloved icons, and game changers.\n\nIn EA SPORTS™ NHL 26, your path to glory begins with a fresh crop of Icon releases, including a free Patrice Bergeron Icon Base Item. On December 15, redeem a World Juniors HUT Choice Pack — your pick of Gavin McKenna, Porter Martone, James Hagens, or Cole Eiserman — and experience all-new World Juniors Chel Week content. Finally, take your look to the next level in HUT and World of Chel with six free limited-edition “Made on iPad” goalie masks.\n\nPlay like a superstar in EA SPORTS NHL® 26. That starts with ICE-Q 2.0, now powered by NHL EDGE data, so your favorite superstars think, move, and play like their on-ice selves. That includes data-informed Attributes and Tendencies which make star players perform in true-to-life fashion, with their playstyles and decision-making game-aware and impactful. A fine-tuned and enhanced arsenal of 28 X-Factors spans five different categories and is driven by unique animations, tactical gameplay outcomes, and tiers of impact, turning each into a formidable on-ice weapon. Superstars now truly feel like superstars.\n\nThe all-new Goalie Crease Control System brings an upgraded awareness between the posts with new close-range and reflex saves that allow for readjustments in reaction to puck deflections, poke checks, and improved AI positioning, giving goalies increased control over the blue paint. In a redesigned Be A Pro mode, each choice you make impacts your career, as you live out the authentic hockey journey from rookie to superstar, with fresh storylines, characters, challenges, and cut scenes.\n\nIt’s time to show out and tell the world to Check My Game.\n\nThis game includes optional in-game purchases of virtual currency that can be used to acquire virtual in-game items, including a random selection of virtual in-game items.\n\n*Conditions & restrictions apply. See https://www.ea.com/games/nhl/nhl-26/game-disclaimers for details.\nAll unspent NHL Points will expire and be removed from your balance after 180 days from date of purchase in Japan. NHL Points cannot be used to purchase HUT Packs in Japan.",
    "images": {
      "Poster": [
        "https://store-images.s-microsoft.com/image/apps.18465.14112647412832778.84c189e6-f1da-44ed-9b30-6d4c0a1a991a.0d105173-7cfa-48fa-a126-f40247669830"
      ],
      "BoxArt": [
        "https://store-images.s-microsoft.com/image/apps.18140.14112647412832778.84c189e6-f1da-44ed-9b30-6d4c0a1a991a.e208f1ae-f24d-40d5-92d1-27b1fc46fe06"
      ],
      "FeaturePromotionalSquareArt": [
        "https://store-images.s-microsoft.com/image/apps.26195.14112647412832778.84c189e6-f1da-44ed-9b30-6d4c0a1a991a.906ba71e-4df7-4b05-8db2-0e0e12dcb5db"
      ],
      "SuperHeroArt": [
        "https://store-images.s-microsoft.com/image/apps.35231.14112647412832778.84c189e6-f1da-44ed-9b30-6d4c0a1a991a.3b38b3cd-b7df-4745-9fe5-4eeeb959540f"
      ],
      "TitledHeroArt": [
        "https://store-images.s-microsoft.com/image/apps.16131.14112647412832778.84c189e6-f1da-44ed-9b30-6d4c0a1a991a.21de1239-1f0c-4511-93ff-a6e07b5fb3b2"
      ],
      "Screenshot": [
        "https://store-images.s-microsoft.com/image/apps.12436.14112647412832778.573a57c5-1e5b-4533-8df0-166897c3e810.10e1ab23-9dad-4716-8f0d-7632924c6011",
        "https://store-images.s-microsoft.com/image/apps.23362.14112647412832778.573a57c5-1e5b-4533-8df0-166897c3e810.6c6b56d8-d125-4ca2-ab2d-0e4803a0f0a2",
        "https://store-images.s-microsoft.com/image/apps.41082.14112647412832778.573a57c5-1e5b-4533-8df0-166897c3e810.2abc24bb-ca47-4109-843b-8aa5876fd11d",
        "https://store-images.s-microsoft.com/image/apps.1522.14112647412832778.573a57c5-1e5b-4533-8df0-166897c3e810.d0aa63cb-b05e-42ec-b2d6-53c88b4b7202",
        "https://store-images.s-microsoft.com/image/apps.24974.14112647412832778.573a57c5-1e5b-4533-8df0-166897c3e810.c3c6a483-c29b-468d-abb9-adf638c35c31",
        "https://store-images.s-microsoft.com/image/apps.922.14112647412832778.573a57c5-1e5b-4533-8df0-166897c3e810.d56df9d5-ee99-4d02-8602-d3a6aee27461",
        "https://store-images.s-microsoft.com/image/apps.9988.14112647412832778.573a57c5-1e5b-4533-8df0-166897c3e810.30af7181-8076-4429-b013-857b5fee413e"
      ]
    },
    "releaseDate": "9998-12-30T00:00:00.0000000Z",
    "userRating": 1.9,
    "pricing": {
      "currencyCode": "EUR",
      "ListPrice": 0,
      "MSRP": 0,
      "WholesalePrice": null
    }
  }
}